perlin_noise/__init__.py
perlin_noise/perlin_noise.py
perlin_noise/rand_vec.py
perlin_noise/tools.py
perlin_noise-1.13.dist-info/METADATA
perlin_noise-1.13.dist-info/WHEEL
perlin_noise-1.13.dist-info/top_level.txt
perlin_noise-1.13.dist-info/RECORD
