Metadata-Version: 2.1
Name: perlin_noise
Version: 1.13
Summary: Python implementation for Perlin Noise with unlimited coordinates space
Author: salaxieb
Author-email: salaxieb.ildar@gmail.com
Classifier: Programming Language :: Python :: 3
Classifier: License :: OSI Approved :: MIT License
Classifier: Operating System :: OS Independent
